flight_tables/__init__.py
flight_tables/flight_parsing.py
flight_tables/flight_tables.py
flight_tables/heathrow_parsing.py
flight_tables/main.py
tests/__init__.py
tests/test_flight_parsing.py
tests/test_heathrow_parsing.py
flight_tables-1.0.dist-info/LICENSE
flight_tables-1.0.dist-info/METADATA
flight_tables-1.0.dist-info/WHEEL
flight_tables-1.0.dist-info/top_level.txt
flight_tables-1.0.dist-info/RECORD
