Metadata-Version: 2.1
Name: flight-tables
Version: 1.0
Summary: Save (Heathrow) Airport Arrivals and Departures to CSV.
Home-page: https://github.com/FergM/flight_tables/
Author: FergM
License: UNKNOWN
Platform: UNKNOWN
Classifier: Programming Language :: Python :: 3
Classifier: License :: OSI Approved :: MIT License
Classifier: Operating System :: OS Independent
Requires-Python: >=3.6
Requires-Dist: bs4 (>=0.0.1)
Requires-Dist: pandas (>=0.25.3)
Requires-Dist: requests (>=2.23.0)
